{
  "name": "도사",
  "difficulty": "★★",
  "skills": [
    {
      "type": "패시브",
      "name": "도력",
      "desc": "바람지대 위에서 이동속도가 증가한다. 바람지대 위에서 선풍 또는 풍인 사용 시 바람지대를 소모해 보호막을 얻는다.",
      "detail": "이동속도 20%증가, 보호막량 2, 보호막 지속시간 2.5초"
    },
    {
      "type": "무기스킬",
      "name": "선풍",
      "desc": "3개의 바람을 날려 각각 피해를 입힌다. 바람지대 위에서 사용 시 더 큰 바람을 날려 사거리 끝까지 가거나 적에게 적중 시 회오리를 일으켜 지속피해를 입힌다. 강화스킬은 쿨타임 없이 바람지대 위에서 사용가능하다",
      "detail": "사거리 14칸, 쿨타임 5초, 피해량 각각 3 (한번 맞은 적은 다음부터 60%의 피해를 입음) 강화스킬 범위 3칸, 피해량 0.5초당 2.6 지속시간 2초, 벽통과가능"
    },
    {
      "type": "일반스킬",
      "name": "경운",
      "desc": "바라본 방향으로 도약하며 5초동안 유지되는 바람지대를 생성한다. 도착 이후 근처 3명에게 기류를 보내 피해를 입힌다. 스킬 적중 시 쿨다운이 0.7초 감소한다.",
      "detail": "쿨타임 9초, 돌진거리 6칸, 피해 범위 5칸, 피해량 2.2, 바람지대 범위 4칸"
    },
    {
      "type": "일반스킬",
      "name": "풍인",
      "desc": "바람을 일으켜 적에게 피해를 입히고 둔화시킨다. 바람지대 위에서 사용 시 뒤로 밀쳐낸다. 강화스킬은 쿨타임 없이 바람지대 위에서 사용가능하다 다른 캐릭터와 달리 Q스킬 또한 F스킬처럼 쿨타임이 돈다.",
      "detail": "쿨타임 7.5초, 피해량 3.5, 사거리 8칸, 둔화 1 2초, 강화 피해량 6"
    },
    {
      "type": "특수스킬",
      "name": "풍류운산(風流雲散)",
      "desc": "지정 위치에 학을 떨궈 피해를 입히고 둔화시킨다. 학은 1초 뒤 다시 날아오르며 적들에게 피해를 입히고 공중으로 띄운다. 해당 스킬은 일회용 스킬 대신으로 일회용 스킬이 2번 갱신될 때마다 사용 가능하다.",
      "detail": "사거리 18칸, 범위 4칸, 1타 피해량 4.5, 둔화 2 1초, 2타 피해량 6"
    }
  ],
  "gadget": "지정 위치에 산수화를 소환해 잠시 뒤 범위 내 가장 가까운 적을 그림 속에 가둔다. 자기 자신 또한 가둘 수 있다."
}